{
  "css/chat_box.css": "css/chat_box-3a78a617fb.css",
  "css/footer.css": "css/footer-d02a8a49c6.css",
  "css/header.css": "css/header-d993d814bb.css",
  "css/home.css": "css/home-43dafa54b8.css",
  "css/layout.css": "css/layout-9025220661.css",
  "css/user_profile.css": "css/user_profile-ff8def9e14.css",
  "css/user_sign_in.css": "css/user_sign_in-027d4af1a5.css",
  "css/user_sign_up.css": "css/user_sign_up-7704203754.css",
  "images/logo.png": "images/logo-6169073561.png",
  "js/chat_engine.js": "js/chat_engine-c87ab25987.js",
  "js/confirm-password.js": "js/confirm-password-f0e900f6f2.js",
  "js/home_post_comments.js": "js/home_post_comments-17d4d4c772.js",
  "js/home_posts.js": "js/home_posts-1a633d8412.js",
  "js/password-eye-sign-up.js": "js/password-eye-sign-up-1a3aebee53.js",
  "js/password-eye.js": "js/password-eye-28dfc234b1.js",
  "js/toggle_likes.js": "js/toggle_likes-0e3d81481c.js"
}